torch_pca/__init__.py
torch_pca/_version.py
torch_pca/ncompo.py
torch_pca/pca_main.py
torch_pca/random_svd.py
torch_pca/svd.py
torch_pca-1.1.0.dist-info/licenses/LICENSE
torch_pca-1.1.0.dist-info/METADATA
torch_pca-1.1.0.dist-info/WHEEL
torch_pca-1.1.0.dist-info/top_level.txt
torch_pca-1.1.0.dist-info/RECORD
