Metadata-Version: 2.4
Name: torch_pca
Version: 1.1.0
Summary: PyTorch implementation of PCA (similar to sklearn PCA).
Author-email: Valentin Goldite <valentin.goldite@gmail.com>
Project-URL: Source, https://github.com/valentingol/torch_pca
Keywords: principal component analysis,PCA,pytorch,torch
Classifier: Programming Language :: Python :: 3
Requires-Python: >=3.8
License-File: LICENSE
Requires-Dist: torch
Dynamic: license-file
